Workbook

Sheet TAM SAM SOM Sizing
A1: NovaHome International Expansion — TAM / SAM / SOM Market Sizing Model
A2: Dynamic Top-Down & Bottom-Up Multi-Market Sizing (2026–2029) | Denominated in USD Millions
A4: Model Legend: | B4: Input / Benchmark Data | D4: Assumption Cell (Editable) | F4: Calculated Formula (Dynamic)
A6: Country | B6: Population (M) | C6: Urban % | D6: Disp. Income ($) | E6: Fitness % | F6: Total Fitness TAM ($M) | G6: Mid-Market Segment % | H6: Top-Down SAM ($M) | I6: Achievable Share % | J6: Top-Down SOM ($M) | K6: HH Size (Est) | L6: Total HH (M) | M6: Qualifying HH (k) | N6: Annual Buy Rate % | O6: Annual Category Units | P6: Bottom-Up SAM ($M) | Q6: Bottom-Up SOM ($M)
A7: United States | B7: 336.5 | C7: 0.832 | D7: 54800 | E7: 0.385 | F7: 4200 | G7: 0.4 | H7: =F7*G7 | I7: 0.08 | J7: =H7*I7 | K7: 2.5 | L7: =B7/K7 | M7: =L7*C7*E7*1000 | N7: 0.1 | O7: =M7*N7*10 | P7: =(O7*950*0.40)/1000000 | Q7: =P7*I7
A8: Canada | B8: 40.5 | C8: 0.818 | D8: 42600 | E8: 0.34 | F8: 410 | G8: 0.4 | H8: =F8*G8 | I8: 0.05 | J8: =H8*I8 | K8: 2.5 | L8: =B8/K8 | M8: =L8*C8*E8*1000 | N8: 0.1 | O8: =M8*N8*10 | P8: =(O8*950*0.40)/1000000 | Q8: =P8*I8
A9: United Kingdom | B9: 68.2 | C9: 0.845 | D9: 38400 | E9: 0.315 | F9: 650 | G9: 0.4 | H9: =F9*G9 | I9: 0.03 | J9: =H9*I9 | K9: 2.5 | L9: =B9/K9 | M9: =L9*C9*E9*1000 | N9: 0.1 | O9: =M9*N9*10 | P9: =(O9*950*0.40)/1000000 | Q9: =P9*I9
A10: Germany | B10: 84.4 | C10: 0.778 | D10: 41200 | E10: 0.29 | F10: 780 | G10: 0.4 | H10: =F10*G10 | I10: 0.03 | J10: =H10*I10 | K10: 2.5 | L10: =B10/K10 | M10: =L10*C10*E10*1000 | N10: 0.1 | O10: =M10*N10*10 | P10: =(O10*950*0.40)/1000000 | Q10: =P10*I10
A11: Netherlands | B11: 18 | C11: 0.928 | D11: 43500 | E11: 0.36 | F11: 160 | G11: 0.4 | H11: =F11*G11 | I11: 0.03 | J11: =H11*I11 | K11: 2.5 | L11: =B11/K11 | M11: =L11*C11*E11*1000 | N11: 0.1 | O11: =M11*N11*10 | P11: =(O11*950*0.40)/1000000 | Q11: =P11*I11
A12: Australia | B12: 26.8 | C12: 0.866 | D12: 44100 | E12: 0.41 | F12: 280 | G12: 0.4 | H12: =F12*G12 | I12: 0.03 | J12: =H12*I12 | K12: 2.5 | L12: =B12/K12 | M12: =L12*C12*E12*1000 | N12: 0.1 | O12: =M12*N12*10 | P12: =(O12*950*0.40)/1000000 | Q12: =P12*I12
A13: Singapore | B13: 6 | C13: 1 | D13: 42800 | E13: 0.32 | F13: 65 | G13: 0.4 | H13: =F13*G13 | I13: 0.03 | J13: =H13*I13 | K13: 2.5 | L13: =B13/K13 | M13: =L13*C13*E13*1000 | N13: 0.1 | O13: =M13*N13*10 | P13: =(O13*950*0.40)/1000000 | Q13: =P13*I13
A14: United Arab Emirates | B14: 9.5 | C14: 0.875 | D14: 39200 | E14: 0.275 | F14: 95 | G14: 0.4 | H14: =F14*G14 | I14: 0.03 | J14: =H14*I14 | K14: 2.5 | L14: =B14/K14 | M14: =L14*C14*E14*1000 | N14: 0.1 | O14: =M14*N14*10 | P14: =(O14*950*0.40)/1000000 | Q14: =P14*I14
A15: Saudi Arabia | B15: 36.9 | C15: 0.847 | D15: 26500 | E15: 0.21 | F15: 180 | G15: 0.4 | H15: =F15*G15 | I15: 0.03 | J15: =H15*I15 | K15: 2.5 | L15: =B15/K15 | M15: =L15*C15*E15*1000 | N15: 0.1 | O15: =M15*N15*10 | P15: =(O15*950*0.40)/1000000 | Q15: =P15*I15
A16: India | B16: 1440 | C16: 0.364 | D16: 3200 | E16: 0.095 | F16: 310 | G16: 0.4 | H16: =F16*G16 | I16: 0.03 | J16: =H16*I16 | K16: 2.5 | L16: =B16/K16 | M16: =L16*C16*E16*1000 | N16: 0.1 | O16: =M16*N16*10 | P16: =(O16*950*0.40)/1000000 | Q16: =P16*I16
A17: Total / Average | F17: =SUM(F7:F16) | H17: =SUM(H7:H16) | J17: =SUM(J7:J16)

Sheet Attractiveness Scoring
A1: NovaHome Market Attractiveness Scoring Matrix (Pillar 1)
A2: Multi-Criteria Evaluation (1.0 = Worst, 5.0 = Best) | Weighted Composite Score
A4: Criteria Weights: | B4: 0.25 | C4: 0.2 | D4: 0.2 | E4: 0.15 | F4: 0.1 | G4: 0.1 | H4: 100%
A6: Country | B6: Market Size Score (25%) | C6: Growth Score (20%) | D6: Demand Score (20%) | E6: Competition Score (15%) | F6: Pricing Score (10%) | G6: Regulatory Score (10%) | H6: Weighted Attractiveness Score (1.0-5.0)
A7: United States | B7: 4.99 | C7: 1.58 | D7: 4.8 | E7: 1.2 | F7: 4.98 | G7: 4.5 | H7: =B7*$B$4 + C7*$C$4 + D7*$D$4 + E7*$E$4 + F7*$F$4 + G7*$G$4
A8: Canada | B8: 2.78 | C8: 1.8 | D8: 3.6 | E8: 1.8 | F8: 4.05 | G8: 4.2 | H8: =B8*$B$4 + C8*$C$4 + D8*$D$4 + E8*$E$4 + F8*$F$4 + G8*$G$4
A9: United Kingdom | B9: 3.22 | C9: 2.31 | D9: 4.2 | E9: 1.9 | F9: 3.72 | G9: 3.5 | H9: =B9*$B$4 + C9*$C$4 + D9*$D$4 + E9*$E$4 + F9*$F$4 + G9*$G$4
A10: Germany | B10: 3.39 | C10: 2.6 | D10: 3.9 | E10: 2.4 | F10: 3.94 | G10: 2.8 | H10: =B10*$B$4 + C10*$C$4 + D10*$D$4 + E10*$E$4 + F10*$F$4 + G10*$G$4
A11: Netherlands | B11: 1.89 | C11: 2.45 | D11: 3.4 | E11: 3.1 | F11: 4.12 | G11: 3.9 | H11: =B11*$B$4 + C11*$C$4 + D11*$D$4 + E11*$E$4 + F11*$F$4 + G11*$G$4
A12: Australia | B12: 2.42 | C12: 2.89 | D12: 3.8 | E12: 2.6 | F12: 4.16 | G12: 3.6 | H12: =B12*$B$4 + C12*$C$4 + D12*$D$4 + E12*$E$4 + F12*$F$4 + G12*$G$4
A13: Singapore | B13: 1.04 | C13: 3.33 | D13: 2.2 | E13: 3.3 | F13: 4.06 | G13: 4 | H13: =B13*$B$4 + C13*$C$4 + D13*$D$4 + E13*$E$4 + F13*$F$4 + G13*$G$4
A14: United Arab Emirates | B14: 1.4 | C14: 4.49 | D14: 3.1 | E14: 3.2 | F14: 3.78 | G14: 3.2 | H14: =B14*$B$4 + C14*$C$4 + D14*$D$4 + E14*$E$4 + F14*$F$4 + G14*$G$4
A15: Saudi Arabia | B15: 2 | C15: 5 | D15: 2.8 | E15: 3.5 | F15: 2.81 | G15: 1.9 | H15: =B15*$B$4 + C15*$C$4 + D15*$D$4 + E15*$E$4 + F15*$F$4 + G15*$G$4
A16: India | B16: 2.52 | C16: 5 | D16: 1.5 | E16: 2.2 | F16: 1.02 | G16: 1.4 | H16: =B16*$B$4 + C16*$C$4 + D16*$D$4 + E16*$E$4 + F16*$F$4 + G16*$G$4

Sheet SOM Sensitivity
A1: NovaHome Serviceable Obtainable Market (SOM) Sensitivity Matrix
A2: Impact of Market Share Capture Rates (1.0% to 5.0%) on Annual Revenue Potential ($M USD)
A5: Country | B5: Top-Down SAM ($M) | C5: SOM @ 1% Share | D5: SOM @ 2% Share | E5: SOM @ 3% Share | F5: SOM @ 4% Share | G5: SOM @ 5% Share
A6: United States | B6: ='TAM SAM SOM Sizing'!H7 | C6: =B6*0.01 | D6: =B6*0.02 | E6: =B6*0.03 | F6: =B6*0.04 | G6: =B6*0.05
A7: Canada | B7: ='TAM SAM SOM Sizing'!H8 | C7: =B7*0.01 | D7: =B7*0.02 | E7: =B7*0.03 | F7: =B7*0.04 | G7: =B7*0.05
A8: United Kingdom | B8: ='TAM SAM SOM Sizing'!H9 | C8: =B8*0.01 | D8: =B8*0.02 | E8: =B8*0.03 | F8: =B8*0.04 | G8: =B8*0.05
A9: Germany | B9: ='TAM SAM SOM Sizing'!H10 | C9: =B9*0.01 | D9: =B9*0.02 | E9: =B9*0.03 | F9: =B9*0.04 | G9: =B9*0.05
A10: Netherlands | B10: ='TAM SAM SOM Sizing'!H11 | C10: =B10*0.01 | D10: =B10*0.02 | E10: =B10*0.03 | F10: =B10*0.04 | G10: =B10*0.05
A11: Australia | B11: ='TAM SAM SOM Sizing'!H12 | C11: =B11*0.01 | D11: =B11*0.02 | E11: =B11*0.03 | F11: =B11*0.04 | G11: =B11*0.05
A12: Singapore | B12: ='TAM SAM SOM Sizing'!H13 | C12: =B12*0.01 | D12: =B12*0.02 | E12: =B12*0.03 | F12: =B12*0.04 | G12: =B12*0.05
A13: United Arab Emirates | B13: ='TAM SAM SOM Sizing'!H14 | C13: =B13*0.01 | D13: =B13*0.02 | E13: =B13*0.03 | F13: =B13*0.04 | G13: =B13*0.05
A14: Saudi Arabia | B14: ='TAM SAM SOM Sizing'!H15 | C14: =B14*0.01 | D14: =B14*0.02 | E14: =B14*0.03 | F14: =B14*0.04 | G14: =B14*0.05
A15: India | B15: ='TAM SAM SOM Sizing'!H16 | C15: =B15*0.01 | D15: =B15*0.02 | E15: =B15*0.03 | F15: =B15*0.04 | G15: =B15*0.05

Sheet Assumptions & Sources
A1: NovaHome Market Sizing Model — Assumptions & Governance Register
A2: Audit Log for All Sizing Multipliers, Share Caps, and Baseline Benchmarks
A5: Parameter / Multiplier | B5: Baseline Value | C5: Type | D5: Operational & Strategic Rationale | E5: Primary Source
A6: Mid-Market Connected Segment % | B6: 40.0% | C6: Commercial Assumption | D6: Share of home fitness equipment market in the $600-$1,200 connected tier vs. discount/luxury | E6: Statista Worldwide Fitness Insights (SRC-006)
A7: Target Achievable Market Share (SOM) | B7: 3.0% | C7: Strategic Assumption | D7: Realistic 3-year market share achievable via D2C & 3PL distribution without retail presence | E7: NovaHome Executive Case Brief (NH-STRAT-2026-001)
A8: Domestic US Market Share | B8: 8.0% | C8: Empirical Benchmark | D8: Current NovaHome domestic market share in North American mid-market connected segment | E8: NovaHome FY2025 Internal Financials
A9: Average Household Size | B9: 2.5 Persons | C9: Demographic Standard | D9: Average household size in urban centers across OECD and European nations | E9: OECD Family Database / Eurostat
A10: Annual Hardware Buying / Upgrade Rate | B10: 10.0% | C10: Category Assumption | D10: Reflects an 8-to-10-year product replacement and new customer adoption lifecycle | E10: IHRSA & EuropeActive Market Studies
A11: Average Selling Price (ASP) | B11: $950 USD | C11: Pricing Benchmark | D11: Blended average order value across NovaPulse Bike, Rower, and Strength Station | E11: NovaHome FY2025 Preliminary Accounts
